awreporting/__init__.py
awreporting/accounts.py
awreporting/awreporting.py
awreporting/command_line.py
awreporting/reporting_threads.py
pyaw_reporting-0.0.7.dist-info/LICENSE
pyaw_reporting-0.0.7.dist-info/METADATA
pyaw_reporting-0.0.7.dist-info/WHEEL
pyaw_reporting-0.0.7.dist-info/entry_points.txt
pyaw_reporting-0.0.7.dist-info/top_level.txt
pyaw_reporting-0.0.7.dist-info/RECORD
