Metadata-Version: 2.1
Name: pyaw-reporting
Version: 0.0.7
Summary: AdWords API Reporting in Python
Home-page: https://github.com/gmontamat/pyaw-reporting
Author: Gustavo Montamat
License: UNKNOWN
Keywords: adwords adwords-api adwords-reports googleads awql
Platform: UNKNOWN
Classifier: Development Status :: 4 - Beta
Classifier: Intended Audience :: Developers
Classifier: Topic :: Software Development :: Libraries
Classifier: License :: OSI Approved :: Apache Software License
Classifier: Programming Language :: Python :: 3.6
Classifier: Programming Language :: Python :: 3.7
Classifier: Programming Language :: Python :: 3.8
Requires-Dist: googleads
